alpenstock/__init__.py
alpenstock/lmdb_cache.py
alpenstock/matlab_fn.py
alpenstock/auto_slice/__init__.py
alpenstock/auto_slice/_mixin.py
alpenstock/auto_slice/_types.py
alpenstock/auto_slice/unstructured.py
alpenstock/io/__init__.py
alpenstock/io/io_utils.py
alpenstock/logging/__init__.py
alpenstock/logging/configure_loguru.py
alpenstock/pytree/__init__.py
alpenstock/pytree/builtin_nodes.py
alpenstock/pytree/core.py
alpenstock/settings/__init__.py
alpenstock/settings/core.py
alpenstock/settings/utils.py
alpenstock-1.2.1.dist-info/licenses/LICENSE
alpenstock-1.2.1.dist-info/METADATA
alpenstock-1.2.1.dist-info/WHEEL
alpenstock-1.2.1.dist-info/top_level.txt
alpenstock-1.2.1.dist-info/RECORD
